Workbook

Sheet Read me
A1: Lloyds Living portfolio model
A2: Barratt Redrow portfolio, 980 homes. Prepared by Nishant Vatnal, Analyst.
A5: What this is | B5: A working model of the 980 home portfolio Lloyds Living signed with Barratt Redrow in July 2026. It mirrors the financial model on the web version of this project.
A6: How to use it | B6: Every blue cell is an input. Change one and the whole workbook recalculates. The two levers people ask about most are the void rate and rent growth, both on the Assumptions sheet.
A7: Colour convention | B7: Blue text is an input you can change. Black text is a formula. Green text is a link to another sheet. Yellow fill marks the two key levers.
A9: Confirmed facts | B9: 980 homes across 14 developments. Six counties: Cambridgeshire, Northamptonshire, Nottinghamshire, Merseyside, East Anglia and the West Midlands. 255 homes in East Anglia. First lettings autumn 2026 at Hampton Beach, Peterborough and Burleyfields, Stafford. Every home EPC B or better, many with air source heat pumps, all managed in house. Source: public Lloyds Living announcement, July 2026.
A10: Modelled by me | B10: The twelve site locations other than Hampton Beach and Burleyfields are my own split of the announced counties, so the pipeline can be planned site by site. The Source column on the asset register says which is which. Unit mix, rents, cost per home, running costs, voids and arrears are all my own estimates.
A11: Comparator data | B11: The occupancy sheet uses the 598 homes bought from Barratt Redrow in 2025 as the closest read across for how the new portfolio will let up. The monthly figures are modelled.
A13: Sheets | B13: Assumptions holds every lever. Rent assumptions holds rents and cost per home by region. Asset register holds the stock. Budget and yield turns rent into a return. Occupancy tracks lease up and arrears. Sensitivity shows the yield across a range of voids and rent growth.
A14: Not a Lloyds publication | B14: This is a personal portfolio project. It uses no internal or confidential information.

Sheet Assumptions
A1: Assumptions
A2: Blue cells are inputs. Yellow fill marks the two levers that move the answer most.
A4: Assumption | B4: Value | C4: Where it comes from
A5: Rent growth applied to all rents | B5: 0 | C5: My assumption. Base case holds rents in 2026 money so the yield is not flattered by growth.
A6: Void rate | B6: 0.045 | C6: My assumption. Share of the year an average home sits empty between tenants.
A7: Rent never collected, bad debt | B7: 0.008 | C7: My assumption, set low because these are new build family homes on longer tenancies.
A8: Property management fee | B8: 0.035 | C8: My assumption. Internal recharge for the in house team. No external agent fee applies.
A9: Repairs and maintenance per home | B9: 550 | C9: My assumption. Low in early years because the stock is new and EPC B or better.
A10: Insurance per home | B10: 185 | C10: My assumption.
A11: Estate and service charges per home | B11: 140 | C11: My assumption. Estate charges on new build developments.
A12: Letting and turnover costs per home | B12: 95 | C12: My assumption. Marketing, referencing and turnaround between tenancies.
A13: Compliance and safety checks per home | B13: 75 | C13: My assumption. Gas, electrical and alarm testing.
A14: Total running cost per home | B14: =SUM(B9:B13) -> 1045 | C14: Sum of the five lines above.
A15: Acquisition costs | B15: 0.018 | C15: My assumption. Legal, tax and due diligence on purchase.
A16: Comparator cohort, homes | B16: 598 | C16: Real. Homes bought from Barratt Redrow in 2025, used as the lease up comparator.

Sheet Rent assumptions
A1: Rent assumptions by region
A2: Monthly asking rents in 2026 money, and the all in cost of buying a home in each region.
A4: Region | B4: 1 bed | C4: 2 bed | D4: 3 bed | E4: 4 bed | F4: Cost per home
A5: Cambridgeshire and Northamptonshire | B5: 850 | C5: 1025 | D5: 1250 | E5: 1495 | F5: 268000
A6: East Anglia | B6: 795 | C6: 950 | D6: 1175 | E6: 1425 | F6: 252000
A7: Nottinghamshire | B7: 775 | C7: 925 | D7: 1110 | E7: 1325 | F7: 222000
A8: Merseyside | B8: 725 | C8: 875 | D8: 1050 | E8: 1250 | F8: 205000
A9: West Midlands | B9: 775 | C9: 950 | D9: 1150 | E9: 1375 | F9: 228000
A11: Rents are my own estimates, set from local evidence for the same size of house with a small premium for a new build in our management. Cost per home is a modelled regional average of the purchase price.
A13: Rents with the growth assumption applied
A14: Region | B14: 1 bed | C14: 2 bed | D14: 3 bed | E14: 4 bed | F14: Growth applied
A15: ='Rent assumptions'!A5 -> Cambridgeshire and Northamptonshire | B15: =B5*(1+Assumptions!$B$5) -> 850 | C15: =C5*(1+Assumptions!$B$5) -> 1025 | D15: =D5*(1+Assumptions!$B$5) -> 1250 | E15: =E5*(1+Assumptions!$B$5) -> 1495 | F15: =Assumptions!$B$5 -> 0
A16: ='Rent assumptions'!A6 -> East Anglia | B16: =B6*(1+Assumptions!$B$5) -> 795 | C16: =C6*(1+Assumptions!$B$5) -> 950 | D16: =D6*(1+Assumptions!$B$5) -> 1175 | E16: =E6*(1+Assumptions!$B$5) -> 1425 | F16: =Assumptions!$B$5 -> 0
A17: ='Rent assumptions'!A7 -> Nottinghamshire | B17: =B7*(1+Assumptions!$B$5) -> 775 | C17: =C7*(1+Assumptions!$B$5) -> 925 | D17: =D7*(1+Assumptions!$B$5) -> 1110 | E17: =E7*(1+Assumptions!$B$5) -> 1325 | F17: =Assumptions!$B$5 -> 0
A18: ='Rent assumptions'!A8 -> Merseyside | B18: =B8*(1+Assumptions!$B$5) -> 725 | C18: =C8*(1+Assumptions!$B$5) -> 875 | D18: =D8*(1+Assumptions!$B$5) -> 1050 | E18: =E8*(1+Assumptions!$B$5) -> 1250 | F18: =Assumptions!$B$5 -> 0
A19: ='Rent assumptions'!A9 -> West Midlands | B19: =B9*(1+Assumptions!$B$5) -> 775 | C19: =C9*(1+Assumptions!$B$5) -> 950 | D19: =D9*(1+Assumptions!$B$5) -> 1150 | E19: =E9*(1+Assumptions!$B$5) -> 1375 | F19: =Assumptions!$B$5 -> 0
A21: What each region contributes
A22: Region | B22: Homes | C22: Gross rent a year | D22: Weighted average rent a month | E22: Capital | F22: Gross yield on cost
A23: =A5 -> Cambridgeshire and Northamptonshire | B23: =SUMIF('Asset register'!$B$5:$B$18,$A23,'Asset register'!$G$5:$G$18) -> 232 | C23: =SUMIF('Asset register'!$B$5:$B$18,$A23,'Asset register'!$P$5:$P$18) -> 62176000 | D23: =IF(B23=0,0,C23/B23/12) -> 22333.333 | E23: =SUMIF('Asset register'!$B$5:$B$18,$A23,'Asset register'!$O$5:$O$18) -> 804000 | F23: =IF(E23=0,0,C23/E23) -> 77.333333
A24: =A6 -> East Anglia | B24: =SUMIF('Asset register'!$B$5:$B$18,$A24,'Asset register'!$G$5:$G$18) -> 255 | C24: =SUMIF('Asset register'!$B$5:$B$18,$A24,'Asset register'!$P$5:$P$18) -> 64260000 | D24: =IF(B24=0,0,C24/B24/12) -> 21000 | E24: =SUMIF('Asset register'!$B$5:$B$18,$A24,'Asset register'!$O$5:$O$18) -> 504000 | F24: =IF(E24=0,0,C24/E24) -> 127.5
A25: =A7 -> Nottinghamshire | B25: =SUMIF('Asset register'!$B$5:$B$18,$A25,'Asset register'!$G$5:$G$18) -> 173 | C25: =SUMIF('Asset register'!$B$5:$B$18,$A25,'Asset register'!$P$5:$P$18) -> 38406000 | D25: =IF(B25=0,0,C25/B25/12) -> 18500 | E25: =SUMIF('Asset register'!$B$5:$B$18,$A25,'Asset register'!$O$5:$O$18) -> 666000 | F25: =IF(E25=0,0,C25/E25) -> 57.666667
A26: =A8 -> Merseyside | B26: =SUMIF('Asset register'!$B$5:$B$18,$A26,'Asset register'!$G$5:$G$18) -> 165 | C26: =SUMIF('Asset register'!$B$5:$B$18,$A26,'Asset register'!$P$5:$P$18) -> 33825000 | D26: =IF(B26=0,0,C26/B26/12) -> 17083.333 | E26: =SUMIF('Asset register'!$B$5:$B$18,$A26,'Asset register'!$O$5:$O$18) -> 615000 | F26: =IF(E26=0,0,C26/E26) -> 55
A27: =A9 -> West Midlands | B27: =SUMIF('Asset register'!$B$5:$B$18,$A27,'Asset register'!$G$5:$G$18) -> 155 | C27: =SUMIF('Asset register'!$B$5:$B$18,$A27,'Asset register'!$P$5:$P$18) -> 35340000 | D27: =IF(B27=0,0,C27/B27/12) -> 19000 | E27: =SUMIF('Asset register'!$B$5:$B$18,$A27,'Asset register'!$O$5:$O$18) -> 684000 | F27: =IF(E27=0,0,C27/E27) -> 51.666667
A28: Portfolio | B28: =SUM(B23:B27) -> 980 | C28: =SUM(C23:C27) -> 234007000 | D28: =C28/B28/12 -> 19898.554 | E28: =SUM(E23:E27) -> 3273000 | F28: =C28/E28 -> 71.496181

Sheet Asset register
A1: Asset register
A2: Every site, the capital it takes and the rent it makes once it is full. 980 homes across 14 developments.
A4: Site | B4: Region | C4: 1 bed | D4: 2 bed | E4: 3 bed | F4: 4 bed | G4: Homes | H4: EPC | I4: First handover | J4: 2026 | K4: 2027 | L4: 2028 | M4: 2029 | N4: Check | O4: Cost per home | P4: Capital | Q4: Gross rent a year | R4: Gross yield on cost | S4: Source
A5: Hampton Beach, Peterborough | B5: Cambridgeshire and Northamptonshire | C5: 10 | D5: 28 | E5: 42 | F5: 16 | G5: =SUM(C5:F5) -> 96 | H5: A | I5: Autumn 2026 | J5: 34 | K5: 62 | L5: 0 | M5: 0 | N5: =G5-SUM(J5:M5) -> 0 | O5: =VLOOKUP($B5,'Rent assumptions'!$A$5:$F$9,6,0) -> 268000 | P5: =G5*O5 -> 25728000 | Q5: =(C5*VLOOKUP($B5,'Rent assumptions'!$A$5:$F$9,2,0)+D5*VLOOKUP($B5,'Rent assumptions'!$A$5:$F$9,3,0)+E5*VLOOKUP($B5,'Rent assumptions'!$A$5:$F$9,4,0)+F5*VLOOKUP($B5,'Rent assumptions'!$A$5:$F$9,5,0))*12*(1+Assumptions!$B$5) -> 1363440 | R5: =P5/O5 -> 96 | S5: Named in announcement
A6: Wellingborough | B6: Cambridgeshire and Northamptonshire | C6: 6 | D6: 20 | E6: 34 | F6: 14 | G6: =SUM(C6:F6) -> 74 | H6: B | I6: H1 2027 | J6: 0 | K6: 40 | L6: 34 | M6: 0 | N6: =G6-SUM(J6:M6) -> 0 | O6: =VLOOKUP($B6,'Rent assumptions'!$A$5:$F$9,6,0) -> 268000 | P6: =G6*O6 -> 19832000 | Q6: =(C6*VLOOKUP($B6,'Rent assumptions'!$A$5:$F$9,2,0)+D6*VLOOKUP($B6,'Rent assumptions'!$A$5:$F$9,3,0)+E6*VLOOKUP($B6,'Rent assumptions'!$A$5:$F$9,4,0)+F6*VLOOKUP($B6,'Rent assumptions'!$A$5:$F$9,5,0))*12*(1+Assumptions!$B$5) -> 1068360 | R6: =P6/O6 -> 74 | S6: Modelled site split
A7: Kettering | B7: Cambridgeshire and Northamptonshire | C7: 4 | D7: 17 | E7: 28 | F7: 13 | G7: =SUM(C7:F7) -> 62 | H7: B | I7: H2 2028 | J7: 0 | K7: 0 | L7: 36 | M7: 26 | N7: =G7-SUM(J7:M7) -> 0 | O7: =VLOOKUP($B7,'Rent assumptions'!$A$5:$F$9,6,0) -> 268000 | P7: =G7*O7 -> 16616000 | Q7: =(C7*VLOOKUP($B7,'Rent assumptions'!$A$5:$F$9,2,0)+D7*VLOOKUP($B7,'Rent assumptions'!$A$5:$F$9,3,0)+E7*VLOOKUP($B7,'Rent assumptions'!$A$5:$F$9,4,0)+F7*VLOOKUP($B7,'Rent assumptions'!$A$5:$F$9,5,0))*12*(1+Assumptions!$B$5) -> 903120 | R7: =P7/O7 -> 62 | S7: Modelled site split
A8: Hucknall | B8: Nottinghamshire | C8: 6 | D8: 19 | E8: 30 | F8: 13 | G8: =SUM(C8:F8) -> 68 | H8: B | I8: H2 2027 | J8: 0 | K8: 38 | L8: 30 | M8: 0 | N8: =G8-SUM(J8:M8) -> 0 | O8: =VLOOKUP($B8,'Rent assumptions'!$A$5:$F$9,6,0) -> 222000 | P8: =G8*O8 -> 15096000 | Q8: =(C8*VLOOKUP($B8,'Rent assumptions'!$A$5:$F$9,2,0)+D8*VLOOKUP($B8,'Rent assumptions'!$A$5:$F$9,3,0)+E8*VLOOKUP($B8,'Rent assumptions'!$A$5:$F$9,4,0)+F8*VLOOKUP($B8,'Rent assumptions'!$A$5:$F$9,5,0))*12*(1+Assumptions!$B$5) -> 873000 | R8: =P8/O8 -> 68 | S8: Modelled site split
A9: Newark | B9: Nottinghamshire | C9: 4 | D9: 15 | E9: 27 | F9: 12 | G9: =SUM(C9:F9) -> 58 | H9: B | I9: H2 2028 | J9: 0 | K9: 0 | L9: 30 | M9: 28 | N9: =G9-SUM(J9:M9) -> 0 | O9: =VLOOKUP($B9,'Rent assumptions'!$A$5:$F$9,6,0) -> 222000 | P9: =G9*O9 -> 12876000 | Q9: =(C9*VLOOKUP($B9,'Rent assumptions'!$A$5:$F$9,2,0)+D9*VLOOKUP($B9,'Rent assumptions'!$A$5:$F$9,3,0)+E9*VLOOKUP($B9,'Rent assumptions'!$A$5:$F$9,4,0)+F9*VLOOKUP($B9,'Rent assumptions'!$A$5:$F$9,5,0))*12*(1+Assumptions!$B$5) -> 754140 | R9: =P9/O9 -> 58 | S9: Modelled site split
A10: Bingham | B10: Nottinghamshire | C10: 3 | D10: 12 | E10: 22 | F10: 10 | G10: =SUM(C10:F10) -> 47 | H10: B | I10: H1 2029 | J10: 0 | K10: 0 | L10: 0 | M10: 47 | N10: =G10-SUM(J10:M10) -> 0 | O10: =VLOOKUP($B10,'Rent assumptions'!$A$5:$F$9,6,0) -> 222000 | P10: =G10*O10 -> 10434000 | Q10: =(C10*VLOOKUP($B10,'Rent assumptions'!$A$5:$F$9,2,0)+D10*VLOOKUP($B10,'Rent assumptions'!$A$5:$F$9,3,0)+E10*VLOOKUP($B10,'Rent assumptions'!$A$5:$F$9,4,0)+F10*VLOOKUP($B10,'Rent assumptions'!$A$5:$F$9,5,0))*12*(1+Assumptions!$B$5) -> 613140 | R10: =P10/O10 -> 47 | S10: Modelled site split
A11: St Helens | B11: Merseyside | C11: 6 | D11: 20 | E11: 30 | F11: 10 | G11: =SUM(C11:F11) -> 66 | H11: A | I11: H2 2027 | J11: 0 | K11: 30 | L11: 36 | M11: 0 | N11: =G11-SUM(J11:M11) -> 0 | O11: =VLOOKUP($B11,'Rent assumptions'!$A$5:$F$9,6,0) -> 205000 | P11: =G11*O11 -> 13530000 | Q11: =(C11*VLOOKUP($B11,'Rent assumptions'!$A$5:$F$9,2,0)+D11*VLOOKUP($B11,'Rent assumptions'!$A$5:$F$9,3,0)+E11*VLOOKUP($B11,'Rent assumptions'!$A$5:$F$9,4,0)+F11*VLOOKUP($B11,'Rent assumptions'!$A$5:$F$9,5,0))*12*(1+Assumptions!$B$5) -> 790200 | R11: =P11/O11 -> 66 | S11: Modelled site split
A12: Prescot | B12: Merseyside | C12: 5 | D12: 16 | E12: 25 | F12: 9 | G12: =SUM(C12:F12) -> 55 | H12: B | I12: H1 2028 | J12: 0 | K12: 0 | L12: 25 | M12: 30 | N12: =G12-SUM(J12:M12) -> 0 | O12: =VLOOKUP($B12,'Rent assumptions'!$A$5:$F$9,6,0) -> 205000 | P12: =G12*O12 -> 11275000 | Q12: =(C12*VLOOKUP($B12,'Rent assumptions'!$A$5:$F$9,2,0)+D12*VLOOKUP($B12,'Rent assumptions'!$A$5:$F$9,3,0)+E12*VLOOKUP($B12,'Rent assumptions'!$A$5:$F$9,4,0)+F12*VLOOKUP($B12,'Rent assumptions'!$A$5:$F$9,5,0))*12*(1+Assumptions!$B$5) -> 661500 | R12: =P12/O12 -> 55 | S12: Modelled site split
A13: Kirkby | B13: Merseyside | C13: 4 | D13: 13 | E13: 20 | F13: 7 | G13: =SUM(C13:F13) -> 44 | H13: B | I13: H1 2029 | J13: 0 | K13: 0 | L13: 0 | M13: 44 | N13: =G13-SUM(J13:M13) -> 0 | O13: =VLOOKUP($B13,'Rent assumptions'!$A$5:$F$9,6,0) -> 205000 | P13: =G13*O13 -> 9020000 | Q13: =(C13*VLOOKUP($B13,'Rent assumptions'!$A$5:$F$9,2,0)+D13*VLOOKUP($B13,'Rent assumptions'!$A$5:$F$9,3,0)+E13*VLOOKUP($B13,'Rent assumptions'!$A$5:$F$9,4,0)+F13*VLOOKUP($B13,'Rent assumptions'!$A$5:$F$9,5,0))*12*(1+Assumptions!$B$5) -> 528300 | R13: =P13/O13 -> 44 | S13: Modelled site split
A14: Burleyfields, Stafford | B14: West Midlands | C14: 7 | D14: 23 | E14: 40 | F14: 18 | G14: =SUM(C14:F14) -> 88 | H14: A | I14: Autumn 2026 | J14: 28 | K14: 60 | L14: 0 | M14: 0 | N14: =G14-SUM(J14:M14) -> 0 | O14: =VLOOKUP($B14,'Rent assumptions'!$A$5:$F$9,6,0) -> 228000 | P14: =G14*O14 -> 20064000 | Q14: =(C14*VLOOKUP($B14,'Rent assumptions'!$A$5:$F$9,2,0)+D14*VLOOKUP($B14,'Rent assumptions'!$A$5:$F$9,3,0)+E14*VLOOKUP($B14,'Rent assumptions'!$A$5:$F$9,4,0)+F14*VLOOKUP($B14,'Rent assumptions'!$A$5:$F$9,5,0))*12*(1+Assumptions!$B$5) -> 1176300 | R14: =P14/O14 -> 88 | S14: Named in announcement
A15: Tamworth | B15: West Midlands | C15: 3 | D15: 11 | E15: 18 | F15: 8 | G15: =SUM(C15:F15) -> 40 | H15: B | I15: H1 2028 | J15: 0 | K15: 0 | L15: 40 | M15: 0 | N15: =G15-SUM(J15:M15) -> 0 | O15: =VLOOKUP($B15,'Rent assumptions'!$A$5:$F$9,6,0) -> 228000 | P15: =G15*O15 -> 9120000 | Q15: =(C15*VLOOKUP($B15,'Rent assumptions'!$A$5:$F$9,2,0)+D15*VLOOKUP($B15,'Rent assumptions'!$A$5:$F$9,3,0)+E15*VLOOKUP($B15,'Rent assumptions'!$A$5:$F$9,4,0)+F15*VLOOKUP($B15,'Rent assumptions'!$A$5:$F$9,5,0))*12*(1+Assumptions!$B$5) -> 533700 | R15: =P15/O15 -> 40 | S15: Modelled site split
A16: Rugeley | B16: West Midlands | C16: 2 | D16: 7 | E16: 12 | F16: 6 | G16: =SUM(C16:F16) -> 27 | H16: B | I16: H1 2029 | J16: 0 | K16: 0 | L16: 0 | M16: 27 | N16: =G16-SUM(J16:M16) -> 0 | O16: =VLOOKUP($B16,'Rent assumptions'!$A$5:$F$9,6,0) -> 228000 | P16: =G16*O16 -> 6156000 | Q16: =(C16*VLOOKUP($B16,'Rent assumptions'!$A$5:$F$9,2,0)+D16*VLOOKUP($B16,'Rent assumptions'!$A$5:$F$9,3,0)+E16*VLOOKUP($B16,'Rent assumptions'!$A$5:$F$9,4,0)+F16*VLOOKUP($B16,'Rent assumptions'!$A$5:$F$9,5,0))*12*(1+Assumptions!$B$5) -> 363000 | R16: =P16/O16 -> 27 | S16: Modelled site split
... A18: Thetford | B18: East Anglia | C18: 9 | D18: 31 | E18: 53 | F18: 24 | G18: =SUM(C18:F18) -> 117 | H18: A | I18: H1 2028 | J18: 0 | K18: 0 | L18: 55 | M18: 62 | N18: =G18-SUM(J18:M18) -> 0 | O18: =VLOOKUP($B18,'Rent assumptions'!$A$5:$F$9,6,0) -> 252000 | P18: =G18*O18 -> 29484000 | Q18: =(C18*VLOOKUP($B18,'Rent assumptions'!$A$5:$F$9,2,0)+D18*VLOOKUP($B18,'Rent assumptions'!$A$5:$F$9,3,0)+E18*VLOOKUP($B18,'Rent assumptions'!$A$5:$F$9,4,0)+F18*VLOOKUP($B18,'Rent assumptions'!$A$5:$F$9,5,0))*12*(1+Assumptions!$B$5) -> 1596960 | R18: =P18/O18 -> 117 | S18: Modelled site split
A19: Portfolio | B19: Five regions | C19: =SUM(C5:C18) -> 80 | D19: =SUM(D5:D18) -> 269 | E19: =SUM(E5:E18) -> 443 | F19: =SUM(F5:F18) -> 188 | G19: =SUM(G5:G18) -> 980 | J19: =SUM(J5:J18) -> 62 | K19: =SUM(K5:K18) -> 278 | L19: =SUM(L5:L18) -> 338 | M19: =SUM(M5:M18) -> 302 | N19: =SUM(N5:N18) -> 0 | O19: =P19/G19 -> 238782.65 | P19: =SUM(P5:P18) -> 234007000 | Q19: =SUM(Q5:Q18) -> 13104900 | R19: =Q19/P19 -> 0.056002171
A21: Check column must read zero on every row. It confirms the year by year phasing adds back to the total homes on that site.
A22: Hampton Beach and Burleyfields are named in the Lloyds Living announcement. The other twelve locations are my own split of the announced counties so the pipeline can be planned site by site.

Sheet Budget and yield
A1: Budget and stabilised yield
A2: The whole portfolio once it is full and settled, so 2030 in practice. Costs are annual.
A4: Line | B4: Amount a year | C4: Share of rent | D4: Per home
A5: Rent a year with every home let | B5: ='Asset register'!$Q$19 -> 13104900 | C5: =B5/$B$5 -> 1 | D5: =ABS(B5)/'Asset register'!$G$19 -> 13372.347
A6: Empty homes | B6: =-$B$5*Assumptions!$B$6 -> -589720.5 | C6: =B6/$B$5 -> -0.045 | D6: =ABS(B6)/'Asset register'!$G$19 -> 601.75561
A7: Rent never collected | B7: =-$B$5*Assumptions!$B$7 -> -104839.2 | C7: =B7/$B$5 -> -0.008 | D7: =ABS(B7)/'Asset register'!$G$19 -> 106.97878
A8: Rent actually collected | B8: =SUM(B5:B7) -> 12410340 | C8: =B8/$B$5 -> 0.947 | D8: =ABS(B8)/'Asset register'!$G$19 -> 12663.613
A9: Property management, our own team | B9: =-$B$5*Assumptions!$B$8 -> -458671.5 | C9: =B9/$B$5 -> -0.035 | D9: =ABS(B9)/'Asset register'!$G$19 -> 468.03214
A10: Repairs and maintenance | B10: =-'Asset register'!$G$19*Assumptions!$B$9 -> -539000 | C10: =B10/$B$5 -> -0.041129654 | D10: =ABS(B10)/'Asset register'!$G$19 -> 550
A11: Insurance | B11: =-'Asset register'!$G$19*Assumptions!$B$10 -> -181300 | C11: =B11/$B$5 -> -0.01383452 | D11: =ABS(B11)/'Asset register'!$G$19 -> 185
A12: Estate and service charges | B12: =-'Asset register'!$G$19*Assumptions!$B$11 -> -137200 | C12: =B12/$B$5 -> -0.010469366 | D12: =ABS(B12)/'Asset register'!$G$19 -> 140
A13: Letting and turnover costs | B13: =-'Asset register'!$G$19*Assumptions!$B$12 -> -93100 | C13: =B13/$B$5 -> -0.0071042129 | D13: =ABS(B13)/'Asset register'!$G$19 -> 95
A14: Compliance and safety checks | B14: =-'Asset register'!$G$19*Assumptions!$B$13 -> -73500 | C14: =B14/$B$5 -> -0.0056085892 | D14: =ABS(B14)/'Asset register'!$G$19 -> 75
A15: Net operating income | B15: =B8+SUM(B9:B14) -> 10927569 | C15: =B15/$B$5 -> 0.83385366 | D15: =ABS(B15)/'Asset register'!$G$19 -> 11150.58
A17: Capital and return
A18: Purchase price | B18: ='Asset register'!$P$19 -> 234007000
A19: Acquisition costs | B19: =B18*Assumptions!$B$15 -> 4212126
A20: Total capital | B20: =B18+B19 -> 238219126
A21: Gross yield on total capital | B21: =B5/B20 -> 0.055011956
A22: Net stabilised yield | B22: =B15/B20 -> 0.04587192
A23: Net operating income per home | B23: =B15/'Asset register'!$G$19 -> 11150.58
A24: Homes | B24: ='Asset register'!$G$19 -> 980
A26: There is no external letting agent fee in this budget because every home is managed by our own team. At a typical agency rate that would be worth about half a million pounds a year.

Sheet Occupancy
A1: Occupancy and arrears
A2: Twelve months on the 598 homes bought from Barratt Redrow in 2025, used as the lease up comparator.
A4: Month | B4: Homes let | C4: Occupancy | D4: Average rent | E4: Rent due | F4: Collection rate | G4: Rent collected | H4: Arrears share | I4: Arrears
A5: Sep 2025 | B5: 512 | C5: =B5/Assumptions!$B$16 -> 0.85618729 | D5: 1065 | E5: =B5*D5 -> 545280 | F5: 0.976 | G5: =E5*F5 -> 532193.28 | H5: 0.024 | I5: =E5*H5 -> 13086.72
A6: Oct 2025 | B6: 528 | C6: =B6/Assumptions!$B$16 -> 0.88294314 | D6: 1065 | E6: =B6*D6 -> 562320 | F6: 0.979 | G6: =E6*F6 -> 550511.28 | H6: 0.022 | I6: =E6*H6 -> 12371.04
A7: Nov 2025 | B7: 541 | C7: =B7/Assumptions!$B$16 -> 0.90468227 | D7: 1068 | E7: =B7*D7 -> 577788 | F7: 0.981 | G7: =E7*F7 -> 566810.03 | H7: 0.021 | I7: =E7*H7 -> 12133.548
A8: Dec 2025 | B8: 549 | C8: =B8/Assumptions!$B$16 -> 0.9180602 | D8: 1068 | E8: =B8*D8 -> 586332 | F8: 0.974 | G8: =E8*F8 -> 571087.37 | H8: 0.026 | I8: =E8*H8 -> 15244.632
A9: Jan 2026 | B9: 556 | C9: =B9/Assumptions!$B$16 -> 0.92976589 | D9: 1072 | E9: =B9*D9 -> 596032 | F9: 0.983 | G9: =E9*F9 -> 585899.46 | H9: 0.019 | I9: =E9*H9 -> 11324.608
A10: Feb 2026 | B10: 562 | C10: =B10/Assumptions!$B$16 -> 0.93979933 | D10: 1072 | E10: =B10*D10 -> 602464 | F10: 0.986 | G10: =E10*F10 -> 594029.5 | H10: 0.016 | I10: =E10*H10 -> 9639.424
A11: Mar 2026 | B11: 569 | C11: =B11/Assumptions!$B$16 -> 0.95150502 | D11: 1078 | E11: =B11*D11 -> 613382 | F11: 0.988 | G11: =E11*F11 -> 606021.42 | H11: 0.014 | I11: =E11*H11 -> 8587.348
A12: Apr 2026 | B12: 573 | C12: =B12/Assumptions!$B$16 -> 0.95819398 | D12: 1085 | E12: =B12*D12 -> 621705 | F12: 0.987 | G12: =E12*F12 -> 613622.83 | H12: 0.015 | I12: =E12*H12 -> 9325.575
A13: May 2026 | B13: 578 | C13: =B13/Assumptions!$B$16 -> 0.96655518 | D13: 1085 | E13: =B13*D13 -> 627130 | F13: 0.99 | G13: =E13*F13 -> 620858.7 | H13: 0.012 | I13: =E13*H13 -> 7525.56
A14: Jun 2026 | B14: 581 | C14: =B14/Assumptions!$B$16 -> 0.97157191 | D14: 1089 | E14: =B14*D14 -> 632709 | F14: 0.991 | G14: =E14*F14 -> 627014.62 | H14: 0.011 | I14: =E14*H14 -> 6959.799
A15: Jul 2026 | B15: 584 | C15: =B15/Assumptions!$B$16 -> 0.97658863 | D15: 1092 | E15: =B15*D15 -> 637728 | F15: 0.992 | G15: =E15*F15 -> 632626.18 | H15: 0.01 | I15: =E15*H15 -> 6377.28
A16: Aug 2026 | B16: 586 | C16: =B16/Assumptions!$B$16 -> 0.97993311 | D16: 1092 | E16: =B16*D16 -> 639912 | F16: 0.992 | G16: =E16*F16 -> 634792.7 | H16: 0.01 | I16: =E16*H16 -> 6399.12
A17: Twelve months | B17: =B16 -> 586 | C17: =B17/Assumptions!$B$16 -> 0.97993311 | E17: =SUM(E5:E16) -> 7242782 | F17: =G17/E17 -> 0.98518323 | G17: =SUM(G5:G16) -> 7135467.4 | I17: =SUM(I5:I16) -> 118974.65
A19: It took about nine months to get from handover to 97 percent let, and collection improved as the estates settled. That is the shape assumed for every new site in the pipeline, which is why the mobilisation spend is front loaded.
A20: Homes let, average rent, collection rate and arrears share are my own modelled figures. The 598 home cohort is real.

Sheet Sensitivity
A1: Sensitivity
A2: Net stabilised yield as the void rate and rent growth move. Voids move the answer more than growth does.
A4: Gross rent at zero growth | B4: ='Asset register'!$Q$19/(1+Assumptions!$B$5) -> 13104900
A5: Homes | B5: ='Asset register'!$G$19 -> 980
A6: Total capital | B6: ='Budget and yield'!$B$20 -> 238219126
A7: Running cost per home | B7: =Assumptions!$B$14 -> 1045
A9: Void rate | B9: Rent growth
A10: Net stabilised yield | B10: 0 | C10: 0.015 | D10: 0.03 | E10: 0.045
A11: 0.02 | B11: =($B$4*(1+B$10)*(1-$A11-Assumptions!$B$7-Assumptions!$B$8)-$B$5*$B$7)/$B$6 -> 0.047247219 | C11: =($B$4*(1+C$10)*(1-$A11-Assumptions!$B$7-Assumptions!$B$8)-$B$5*$B$7)/$B$6 -> 0.048020412 | D11: =($B$4*(1+D$10)*(1-$A11-Assumptions!$B$7-Assumptions!$B$8)-$B$5*$B$7)/$B$6 -> 0.048793605 | E11: =($B$4*(1+E$10)*(1-$A11-Assumptions!$B$7-Assumptions!$B$8)-$B$5*$B$7)/$B$6 -> 0.049566798
A12: 0.03 | B12: =($B$4*(1+B$10)*(1-$A12-Assumptions!$B$7-Assumptions!$B$8)-$B$5*$B$7)/$B$6 -> 0.0466971 | C12: =($B$4*(1+C$10)*(1-$A12-Assumptions!$B$7-Assumptions!$B$8)-$B$5*$B$7)/$B$6 -> 0.047462041 | D12: =($B$4*(1+D$10)*(1-$A12-Assumptions!$B$7-Assumptions!$B$8)-$B$5*$B$7)/$B$6 -> 0.048226982 | E12: =($B$4*(1+E$10)*(1-$A12-Assumptions!$B$7-Assumptions!$B$8)-$B$5*$B$7)/$B$6 -> 0.048991924
A13: 0.045 | B13: =($B$4*(1+B$10)*(1-$A13-Assumptions!$B$7-Assumptions!$B$8)-$B$5*$B$7)/$B$6 -> 0.04587192 | C13: =($B$4*(1+C$10)*(1-$A13-Assumptions!$B$7-Assumptions!$B$8)-$B$5*$B$7)/$B$6 -> 0.046624484 | D13: =($B$4*(1+D$10)*(1-$A13-Assumptions!$B$7-Assumptions!$B$8)-$B$5*$B$7)/$B$6 -> 0.047377048 | E13: =($B$4*(1+E$10)*(1-$A13-Assumptions!$B$7-Assumptions!$B$8)-$B$5*$B$7)/$B$6 -> 0.048129611
A14: 0.06 | B14: =($B$4*(1+B$10)*(1-$A14-Assumptions!$B$7-Assumptions!$B$8)-$B$5*$B$7)/$B$6 -> 0.045046741 | C14: =($B$4*(1+C$10)*(1-$A14-Assumptions!$B$7-Assumptions!$B$8)-$B$5*$B$7)/$B$6 -> 0.045786927 | D14: =($B$4*(1+D$10)*(1-$A14-Assumptions!$B$7-Assumptions!$B$8)-$B$5*$B$7)/$B$6 -> 0.046527113 | E14: =($B$4*(1+E$10)*(1-$A14-Assumptions!$B$7-Assumptions!$B$8)-$B$5*$B$7)/$B$6 -> 0.047267299
A15: 0.075 | B15: =($B$4*(1+B$10)*(1-$A15-Assumptions!$B$7-Assumptions!$B$8)-$B$5*$B$7)/$B$6 -> 0.044221562 | C15: =($B$4*(1+C$10)*(1-$A15-Assumptions!$B$7-Assumptions!$B$8)-$B$5*$B$7)/$B$6 -> 0.04494937 | D15: =($B$4*(1+D$10)*(1-$A15-Assumptions!$B$7-Assumptions!$B$8)-$B$5*$B$7)/$B$6 -> 0.045677178 | E15: =($B$4*(1+E$10)*(1-$A15-Assumptions!$B$7-Assumptions!$B$8)-$B$5*$B$7)/$B$6 -> 0.046404986
A18: Read this as a range, not a forecast. Across the whole grid the yield moves between about 4.4 and 5.0 percent. The void rate moves it more than rent growth does in the early years, which is the argument for spending money on mobilisation rather than hoping the market carries us.
A19: The grid is worked out independently of the Assumptions sheet levers, so it always shows the full range. The Budget and yield sheet shows wherever the levers are currently set.
